insight_plugin/__init__.py
insight_plugin/__main__.py
insight_plugin/black_config.toml
insight_plugin/constants.py
insight_plugin/__pycache__/__init__.cpython-311.pyc
insight_plugin/features/__init__.py
insight_plugin/features/analysis/__init__.py
insight_plugin/features/analysis/controller.py
insight_plugin/features/common/__init__.py
insight_plugin/features/common/builder.py
insight_plugin/features/common/checksum_util.py
insight_plugin/features/common/command_line_util.py
insight_plugin/features/common/common_feature.py
insight_plugin/features/common/docker_util.py
insight_plugin/features/common/dockerspec.py
insight_plugin/features/common/exceptions.py
insight_plugin/features/common/logging_util.py
insight_plugin/features/common/plugin_spec_util.py
insight_plugin/features/common/schema_util.py
insight_plugin/features/common/temp_file_util.py
insight_plugin/features/common/template_util.py
insight_plugin/features/connector_to_plugin/__init__.py
insight_plugin/features/connector_to_plugin/controller.py
insight_plugin/features/connector_to_plugin/manifest_util.py
insight_plugin/features/connector_to_plugin/util.py
insight_plugin/features/connector_to_plugin/help/__init__.py
insight_plugin/features/connector_to_plugin/help/constants.py
insight_plugin/features/connector_to_plugin/help/help_util.py
insight_plugin/features/connector_to_plugin/models/__init__.py
insight_plugin/features/connector_to_plugin/models/actions_schema.py
insight_plugin/features/connector_to_plugin/models/connection_schema.py
insight_plugin/features/connector_to_plugin/models/plugin_schem.py
insight_plugin/features/connector_to_plugin/models/util_schema.py
insight_plugin/features/convert_event_source/__init__.py
insight_plugin/features/convert_event_source/controller.py
insight_plugin/features/convert_event_source/util.py
insight_plugin/features/create/__init__.py
insight_plugin/features/create/controller.py
insight_plugin/features/create/json_generation_util.py
insight_plugin-1.9.22.dist-info/licenses/LICENSE
insight_plugin-1.9.22.dist-info/METADATA
insight_plugin-1.9.22.dist-info/WHEEL
insight_plugin-1.9.22.dist-info/entry_points.txt
insight_plugin-1.9.22.dist-info/top_level.txt
insight_plugin-1.9.22.dist-info/RECORD
