Metadata-Version: 2.4
Name: insight-plugin
Version: 1.9.22
Summary: Tooling for developing plugins for InsightConnect
Home-page: https://github.com/rapid7/insight-plugin
Author: rapid7
Author-email: integrationalliance@rapid7.com
License: MIT
Project-URL: Homepage, https://docs.rapid7.com/insightconnect/getting-started
Project-URL: Documentation, https://docs.rapid7.com/insightconnect/getting-started
Classifier: Programming Language :: Python :: 3
Classifier: License :: OSI Approved :: MIT License
Classifier: Intended Audience :: Developers
Classifier: Development Status :: 5 - Production/Stable
Requires-Python: >=3.0
License-File: LICENSE
Requires-Dist: jinja2==3.1.6
Requires-Dist: pyyaml==6.0.1
Requires-Dist: jsonschema==2.3.0
Requires-Dist: mdutils==1.3.1
Requires-Dist: jq==1.4.0
Requires-Dist: insightconnect-integrations-validators~=2.47
Requires-Dist: markupsafe==2.0.1
Requires-Dist: ruamel.yaml==0.17.21
Requires-Dist: ruamel.yaml.clib==0.2.7
Requires-Dist: semver==3.0.4
Requires-Dist: black==24.10.0
Requires-Dist: parameterized==0.8.1
Requires-Dist: prospector==1.14.1
Requires-Dist: prospector[with_bandit]
Dynamic: author-email
Dynamic: home-page
Dynamic: license
Dynamic: license-file
Dynamic: requires-dist
